p1radup/__init__.py
p1radup/p1radup.py
p1radup/sort.py
p1radup/url_processor.py
p1radup/utils.py
p1radup-2.2.5.dist-info/LICENSE
p1radup-2.2.5.dist-info/METADATA
p1radup-2.2.5.dist-info/WHEEL
p1radup-2.2.5.dist-info/entry_points.txt
p1radup-2.2.5.dist-info/top_level.txt
p1radup-2.2.5.dist-info/RECORD
