Metadata-Version: 2.1
Name: p1radup
Version: 2.2.5
Summary: This tool is designed to process a list of URLs from an input file, remove duplicate query parameters, and save the modified URLs to an output file.
Home-page: https://github.com/iambouali/p1radup
Author: Tarek Bouali
Author-email: contact@tarekbouali.com
License: UNKNOWN
Platform: UNKNOWN
Classifier: Programming Language :: Python :: 3
Classifier: License :: OSI Approved :: MIT License
Classifier: Operating System :: OS Independent
License-File: LICENSE
Requires-Dist: termcolor
Requires-Dist: validators
